packageuser34/__init__.py
packageuser34/addition.py
packageuser34/subtraction.py
packageuser34-0.1.5.dist-info/METADATA
packageuser34-0.1.5.dist-info/WHEEL
packageuser34-0.1.5.dist-info/RECORD
